loggo/__init__.py
loggo/class_decorator.py
loggo/config.py
loggo/decorator.py
loggo/exception.py
loggo/loggo.py
loggo-0.1.0.dist-info/DESCRIPTION.rst
loggo-0.1.0.dist-info/METADATA
loggo-0.1.0.dist-info/RECORD
loggo-0.1.0.dist-info/WHEEL
loggo-0.1.0.dist-info/metadata.json
loggo-0.1.0.dist-info/top_level.txt
tests/tests.py
