Metadata-Version: 2.0
Name: loggo
Version: 0.1.0
Summary: Python logging tools
Home-page: UNKNOWN
Author: Danny McDonald
Author-email: daniel.mcdonald@bitpanda.com
License: UNKNOWN
Keywords: bitpanda utilities
Platform: UNKNOWN
Classifier: Development Status :: 3 - Alpha
Classifier: Topic :: Utilities
Requires-Dist: graypy
Requires-Dist: colorama
